presentations/__init__.py
presentations/info.py
presentations/parser.py
presentations/cli/__init__.py
presentations/cli/gen.py
presentations/cli/main.py
presentations/templates/base.plim
presentations/vendor/revealjs/LICENSE
presentations/vendor/revealjs/README.md
presentations/vendor/revealjs/css/reveal.css
presentations/vendor/revealjs/css/reveal.min.css
presentations/vendor/revealjs/css/print/paper.css
presentations/vendor/revealjs/css/print/pdf.css
presentations/vendor/revealjs/css/theme/README.md
presentations/vendor/revealjs/css/theme/beige.css
presentations/vendor/revealjs/css/theme/blood.css
presentations/vendor/revealjs/css/theme/default.css
presentations/vendor/revealjs/css/theme/moon.css
presentations/vendor/revealjs/css/theme/night.css
presentations/vendor/revealjs/css/theme/serif.css
presentations/vendor/revealjs/css/theme/simple.css
presentations/vendor/revealjs/css/theme/sky.css
presentations/vendor/revealjs/css/theme/solarized.css
presentations/vendor/revealjs/js/reveal.js
presentations/vendor/revealjs/js/reveal.min.js
presentations/vendor/revealjs/lib/css/zenburn.css
presentations/vendor/revealjs/lib/font/league_gothic-webfont.eot
presentations/vendor/revealjs/lib/font/league_gothic-webfont.svg
presentations/vendor/revealjs/lib/font/league_gothic-webfont.ttf
presentations/vendor/revealjs/lib/font/league_gothic-webfont.woff
presentations/vendor/revealjs/lib/js/classList.js
presentations/vendor/revealjs/lib/js/head.min.js
presentations/vendor/revealjs/lib/js/html5shiv.js
presentations/vendor/revealjs/plugin/highlight/highlight.js
presentations/vendor/revealjs/plugin/leap/leap.js
presentations/vendor/revealjs/plugin/markdown/example.html
presentations/vendor/revealjs/plugin/markdown/example.md
presentations/vendor/revealjs/plugin/markdown/markdown.js
presentations/vendor/revealjs/plugin/markdown/marked.js
presentations/vendor/revealjs/plugin/math/math.js
presentations/vendor/revealjs/plugin/multiplex/client.js
Presentations-0.0.2.dist-info/AUTHORS
Presentations-0.0.2.dist-info/LICENSE
Presentations-0.0.2.dist-info/METADATA
Presentations-0.0.2.dist-info/WHEEL
Presentations-0.0.2.dist-info/entry_points.txt
Presentations-0.0.2.dist-info/top_level.txt
Presentations-0.0.2.dist-info/RECORD
