Metadata-Version: 2.1
Name: Presentations
Version: 0.0.2
Summary: Presentations using reveal.js
Home-page: https://maximavanov.com/projects/presentations
Author: Maxim Avanov
Author-email: maxim.avanov@gmail.com
License: UNKNOWN
Keywords: presentation slides revealjs plim mako
Platform: UNKNOWN
Classifier: Development Status :: 1 - Planning
Classifier: Intended Audience :: Developers
Classifier: License :: OSI Approved
Classifier: License :: OSI Approved :: MIT License
Classifier: Programming Language :: Python
Classifier: Programming Language :: Python :: 3
Classifier: Operating System :: POSIX
Requires-Dist: Mako (>=0.9.1)
Requires-Dist: Plim (>=0.9.5)
Requires-Dist: Pygments (>=1.6)
